setup.py
PythonExacttarget.egg-info/PKG-INFO
PythonExacttarget.egg-info/SOURCES.txt
PythonExacttarget.egg-info/dependency_links.txt
PythonExacttarget.egg-info/requires.txt
PythonExacttarget.egg-info/top_level.txt
exacttarget/__init__.py
exacttarget/api.py