Metadata-Version: 1.0
Name: PythonExacttarget
Version: 0.1.0
Summary: Python Wrapper for Exact Target SOAP API
Home-page: https://github.com/damilare/pythonexacttarget/
Author: Matthew Black
Author-email: consult@jbadigital.com
License: LICENSE.txt
Platform: UNKNOWN
